triple_encoders/TripleEncoders.py
triple_encoders/TripleEncodersForConversationalSequenceModeling.py
triple_encoders/TripleEncodersForSTP.py
triple_encoders/TripleEncodersForSequenceModeling.py
triple_encoders/__init__.py
triple_encoders/trainer.py
triple_encoders/evaluator/EmbeddingsTripleSimilarityEvaluator.py
triple_encoders/evaluator/__init__.py
triple_encoders/losses/CosineSimilarityTripleEncoderLoss.py
triple_encoders/losses/__init__.py
triple_encoders-0.0.2.dist-info/LICENSE
triple_encoders-0.0.2.dist-info/METADATA
triple_encoders-0.0.2.dist-info/NOTICE
triple_encoders-0.0.2.dist-info/WHEEL
triple_encoders-0.0.2.dist-info/top_level.txt
triple_encoders-0.0.2.dist-info/RECORD
