Metadata-Version: 2.1
Name: triple-encoders
Version: 0.0.2
Summary: Distributed Sentence Transformer Representations with Triple Encoders 
Download-URL: https://github.com/UKPLab/arxiv2024-triple-encoders
Author: Justus-Jonas Erker
Author-email: justus-jonas.erker@tu-darmstadt.de
License: Apache License 2.0
Keywords: PyTorch NLP deep learning Sentence Transformer Triple Encoders Dialog Systems
Classifier: Development Status :: 2 - Pre-Alpha
Classifier: License :: OSI Approved :: Apache Software License
Classifier: Programming Language :: Python :: 3.8
Classifier: Topic :: Scientific/Engineering :: Artificial Intelligence
Classifier: Intended Audience :: Science/Research
Requires-Python: >=3.8.0
License-File: LICENSE
License-File: NOTICE
Requires-Dist: datasets ==2.17.0
Requires-Dist: transformers ==4.34.1
Requires-Dist: sentence-transformers ==2.2.2
Requires-Dist: torch ==2.0.1
Requires-Dist: numpy ==1.21.5
Requires-Dist: pandas ==1.4.4
Requires-Dist: tqdm ==4.64.1
